gravify/__init__.py
gravify/avatars/__init__.py
gravify/avatars/exceptions.py
gravify/avatars/generator.py
gravify/avatars/options.py
gravify/exceptions.py
gravify/profiles/__init__.py
gravify/profiles/api.py
gravify/profiles/models.py
gravify/py.typed
gravify/rest_adapter.py
gravify/utils.py
gravify-2.0.0.dist-info/licenses/LICENSE
gravify-2.0.0.dist-info/WHEEL
gravify-2.0.0.dist-info/METADATA
gravify-2.0.0.dist-info/RECORD
