Metadata-Version: 2.4
Name: gravify
Version: 2.0.0
Summary: A library to interface with Gravatar profiles and avatars.
Author: Ben Soyka
Author-email: Ben Soyka <hello@bsoyka.me>
License-Expression: MIT
License-File: LICENSE
Classifier: Intended Audience :: Developers
Classifier: License :: OSI Approved :: MIT License
Classifier: Natural Language :: English
Classifier: Operating System :: OS Independent
Classifier: Programming Language :: Python
Classifier: Programming Language :: Python :: 3
Classifier: Programming Language :: Python :: 3 :: Only
Classifier: Programming Language :: Python :: 3.10
Classifier: Programming Language :: Python :: 3.11
Classifier: Programming Language :: Python :: 3.12
Classifier: Programming Language :: Python :: 3.13
Classifier: Typing :: Typed
Requires-Dist: httpx>=0.28.1
Requires-Dist: pydantic[email]>=2.11.7
Requires-Python: >=3.10
Project-URL: Changelog, https://github.com/bsoyka/gravify/releases
Project-URL: Documentation, https://gravify.readthedocs.io/
Project-URL: Sponsor, https://github.com/sponsors/bsoyka
